mainmethod/__init__.py
mainmethod/mainmethod.py
mainmethod-0.1.0.dist-info/METADATA
mainmethod-0.1.0.dist-info/WHEEL
mainmethod-0.1.0.dist-info/top_level.txt
mainmethod-0.1.0.dist-info/RECORD
