Metadata-Version: 2.1
Name: mainmethod
Version: 0.1.0
Summary: C-Like main method support
Home-page: https://github.com/yankyhoffman/mainmethod
Author: Yanky Hoffman
Author-email: developer.yankyhoffman@gmail.com
License: UNKNOWN
Platform: UNKNOWN
